qute_style/__init__.py
qute_style/dev/__init__.py
qute_style/dev/dev_functions.py
qute_style/dev/mocks.py
qute_style/gen/__init__.py
qute_style/gen/ui_test_window.py
qute_style/gen/ui_whats_new_window.py
qute_style/helper.py
qute_style/py.typed
qute_style/qs_application.py
qute_style/qs_main_window.py
qute_style/qs_message_box.py
qute_style/qute_style.py
qute_style/resources/png_icons/transparent_icon.png
qute_style/resources/svg_icons/accept.svg
qute_style/resources/svg_icons/accept_circle.svg
qute_style/resources/svg_icons/active_menu.svg
qute_style/resources/svg_icons/adb.svg
qute_style/resources/svg_icons/add.svg
qute_style/resources/svg_icons/add_circle.svg
qute_style/resources/svg_icons/admin.svg
qute_style/resources/svg_icons/admin_panel.svg
qute_style/resources/svg_icons/airport_shuttle.svg
qute_style/resources/svg_icons/archive.svg
qute_style/resources/svg_icons/arrow_back.svg
qute_style/resources/svg_icons/arrow_down.svg
qute_style/resources/svg_icons/arrow_right.svg
qute_style/resources/svg_icons/balance.svg
qute_style/resources/svg_icons/blender.svg
qute_style/resources/svg_icons/block.svg
qute_style/resources/svg_icons/bug.svg
qute_style/resources/svg_icons/cake.svg
qute_style/resources/svg_icons/check_circle.svg
qute_style/resources/svg_icons/checked.svg
qute_style/resources/svg_icons/chevron_left.svg
qute_style/resources/svg_icons/child_friendly.svg
qute_style/resources/svg_icons/clipboard.svg
qute_style/resources/svg_icons/close.svg
qute_style/resources/svg_icons/close_circle.svg
qute_style/resources/svg_icons/cloud_done.svg
qute_style/resources/svg_icons/cloud_upload.svg
qute_style/resources/svg_icons/coffee.svg
qute_style/resources/svg_icons/cookie.svg
qute_style/resources/svg_icons/copy.svg
qute_style/resources/svg_icons/cps_trends.svg
qute_style/resources/svg_icons/cruelty_free.svg
qute_style/resources/svg_icons/cyclone.svg
qute_style/resources/svg_icons/delete.svg
qute_style/resources/svg_icons/delete_forever.svg
qute_style-1.0.9.dist-info/LICENSE
qute_style-1.0.9.dist-info/METADATA
qute_style-1.0.9.dist-info/WHEEL
qute_style-1.0.9.dist-info/entry_points.txt
qute_style-1.0.9.dist-info/RECORD
