Metadata-Version: 2.3
Name: qute_style
Version: 1.0.9
Summary: QuteStyle is an expandable application framework for PySide6
License: MIT
Author: Marina Baumgartner, Dairen Gonschior, Tilman Krummeck, Dennis Spitzhorn, Gerhard Trapp, Patrick Zwerschke
Author-email: PS-TF-Entwicklung@tuev-sued.de
Requires-Python: >=3.9,<3.13
Classifier: License :: OSI Approved :: MIT License
Classifier: Programming Language :: Python :: 3
Classifier: Programming Language :: Python :: 3.9
Classifier: Programming Language :: Python :: 3.10
Classifier: Programming Language :: Python :: 3.11
Classifier: Programming Language :: Python :: 3.12
Requires-Dist: PySide6 (==6.9.1)
Project-URL: Repository, https://github.com/TUV-SUD-Product-Service-GmbH/QuteStyle
